jsonsam/__init__.py
jsonsam/jsonsam.py
jsonsam/randdict.py
jsonsam-0.1.1.dist-info/entry_points.txt
jsonsam-0.1.1.dist-info/LICENSE
jsonsam-0.1.1.dist-info/WHEEL
jsonsam-0.1.1.dist-info/METADATA
jsonsam-0.1.1.dist-info/RECORD
