Metadata-Version: 2.1
Name: jsonsam
Version: 0.1.1
Summary: Tool to facilitate editing, splitting and merging of nested JSON and Python dictionaries
Home-page: https://github.com/project705/jsonsam
License: MIT
Keywords: json,split,merge,edit
Author: Eric D. Cohen
Author-email: os@epieye.com
Requires-Python: >=3.8,<4.0
Classifier: Development Status :: 3 - Alpha
Classifier: License :: OSI Approved :: MIT License
Classifier: Programming Language :: Python :: 3
Classifier: Programming Language :: Python :: 3.8
Classifier: Programming Language :: Python :: 3.9
Classifier: Topic :: Text Processing
Classifier: Topic :: Utilities
Requires-Dist: Faker (>=8.1,<9.0)
Requires-Dist: deepdiff (>=5.5,<6.0)
Project-URL: Bug Tracker, https://github.com/project705/jsonsam/issues
